shtuff.py
shtuff-0.4.0.dist-info/licenses/LICENSE.txt
shtuff-0.4.0.dist-info/METADATA
shtuff-0.4.0.dist-info/WHEEL
shtuff-0.4.0.dist-info/entry_points.txt
shtuff-0.4.0.dist-info/top_level.txt
shtuff-0.4.0.dist-info/RECORD
