Metadata-Version: 2.4
Name: shtuff
Version: 0.4.0
Summary: It's like screen's stuff command, without screen
Home-page: https://github.com/jfly/shtuff
Author: Jeremy Fleischman
Author-email: jeremyfleischman@gmail.com
Classifier: Development Status :: 3 - Alpha
Classifier: Intended Audience :: Developers
Classifier: Topic :: Software Development :: Build Tools
Classifier: License :: OSI Approved :: MIT License
Classifier: Programming Language :: Python :: 3
Classifier: Programming Language :: Python :: 3.7
Requires-Python: >=3.7
License-File: LICENSE.txt
Requires-Dist: pexpect
Requires-Dist: setproctitle
Requires-Dist: pyxdg
Requires-Dist: psutil
Requires-Dist: setuptools
Provides-Extra: dev
Requires-Dist: check-manifest; extra == "dev"
Provides-Extra: test
Requires-Dist: coverage; extra == "test"
Dynamic: author
Dynamic: author-email
Dynamic: classifier
Dynamic: description
Dynamic: description-content-type
Dynamic: home-page
Dynamic: license-file
Dynamic: provides-extra
Dynamic: requires-dist
Dynamic: requires-python
Dynamic: summary
